Metadata-Version: 2.1
Name: webuipy
Version: 0.0.1
Summary: Python API Client for A1111 WebUI
Home-page: https://github.com/datamonet
Author: DataMonet LLC
Author-email: support@replicable.art
License: MIT
Classifier: License :: OSI Approved :: MIT License
Classifier: Programming Language :: Python
Classifier: Programming Language :: Python :: 3
License-File: LICENSE
